ProbabPy/__init__.py
ProbabPy-0.1.3.dist-info/DESCRIPTION.rst
ProbabPy-0.1.3.dist-info/METADATA
ProbabPy-0.1.3.dist-info/metadata.json
ProbabPy-0.1.3.dist-info/RECORD
ProbabPy-0.1.3.dist-info/top_level.txt
ProbabPy-0.1.3.dist-info/WHEEL
