Metadata-Version: 2.0
Name: ProbabPy
Version: 0.1.3
Summary: (Multivariate) Probability Distributions
Home-page: https://github.com/MBALearnsToCode/ProbabPy
Author: Vinh Luong (a.k.a. MBALearnsToCode)
Author-email: MBALearnsToCode@UChicago.edu
License: MIT License
Keywords: prob probability distribution
Platform: UNKNOWN
Requires-Dist: FrozenDict
Requires-Dist: HelpyFuncs
Requires-Dist: MathDict
Requires-Dist: MathFunc
Requires-Dist: SciPy
Requires-Dist: SymPy
